pyCADD/__init__.py
pyCADD/__main__.py
pyCADD/Dance/__init__.py
pyCADD/Dance/__main__.py
pyCADD/Dance/common.py
pyCADD/Dance/core.py
pyCADD/Dance/metrics.py
pyCADD/Dance/algorithm/DL.py
pyCADD/Dance/algorithm/__init__.py
pyCADD/Dance/algorithm/consensus.py
pyCADD/Dance/algorithm/default_params.py
pyCADD/Demand/__init__.py
pyCADD/Demand/__main__.py
pyCADD/Demand/cli.py
pyCADD/Demand/config.py
pyCADD/Demand/core.py
pyCADD/Density/__init__.py
pyCADD/Density/__main__.py
pyCADD/Density/base.py
pyCADD/Density/cli.py
pyCADD/Density/core.py
pyCADD/Dock/__init__.py
pyCADD/Dock/__main__.py
pyCADD/Dock/cli.py
pyCADD/Dock/common.py
pyCADD/Dock/const.py
pyCADD/Dock/env.py
pyCADD/Dock/ui.py
pyCADD/Dock/utils.py
pyCADD/Dock/schrodinger/__init__.py
pyCADD/Dock/schrodinger/api.py
pyCADD/Dock/schrodinger/common.py
pyCADD/Dock/schrodinger/config.py
pyCADD/Dock/schrodinger/core.py
pyCADD/Dock/schrodinger/data.py
pyCADD/Dock/schrodinger/ensemble.py
pyCADD/Dock/schrodinger/utils.py
pyCADD/Dynamic/__init__.py
pyCADD/Dynamic/analysis.py
pyCADD/Dynamic/cli.py
pyCADD/Dynamic/common.py
pyCADD/Dynamic/constant.py
pyCADD/Dynamic/core.py
pyCADD/Dynamic/template.py
pyCADD/Dynamic/utils.py
pyCADD/utils/__init__.py
pyCADD/utils/common.py
pyCADD/utils/log.py
pyCADD/utils/tool.py
pyCADD/utils/ui.py
pycadd-2.0.2.dist-info/licenses/LICENSE
pycadd-2.0.2.dist-info/METADATA
pycadd-2.0.2.dist-info/WHEEL
pycadd-2.0.2.dist-info/entry_points.txt
pycadd-2.0.2.dist-info/top_level.txt
pycadd-2.0.2.dist-info/RECORD
