Metadata-Version: 2.4
Name: pyCADD
Version: 2.0.2
Summary: A Python Package for Computer-aid Drug Design
Author-email: "YH. W" <yuhangxmu@stu.xmu.edu.cn>
Maintainer-email: "YH. W" <yuhangxmu@stu.xmu.edu.cn>
License: GPL-3.0
Project-URL: Homepage, https://github.com/CyberCatQ/pyCADD
Project-URL: Repository, https://github.com/CyberCatQ/pyCADD
Project-URL: Documentation, https://cybercatq.github.io/pyCADD/
Project-URL: Bug Reports, https://github.com/CyberCatQ/pyCADD/issues
Keywords: drug-design,computational-chemistry,bioinformatics,molecular-docking
Classifier: Development Status :: 4 - Beta
Classifier: Intended Audience :: Science/Research
Classifier: License :: OSI Approved :: GNU General Public License v3 (GPLv3)
Classifier: Operating System :: OS Independent
Classifier: Programming Language :: Python :: 3
Classifier: Programming Language :: Python :: 3.10
Classifier: Programming Language :: Python :: 3.11
Classifier: Programming Language :: Python :: 3.12
Classifier: Topic :: Scientific/Engineering :: Chemistry
Classifier: Topic :: Scientific/Engineering :: Bio-Informatics
Requires-Python: >=3.10
License-File: LICENSE
Requires-Dist: rich>=10.16
Requires-Dist: concurrent-log-handler>=0.9.20
Requires-Dist: scikit-learn
Requires-Dist: pandas>=1.4.1
Requires-Dist: openpyxl
Requires-Dist: pyyaml>=6.0
Requires-Dist: click
Requires-Dist: scipy
Requires-Dist: xlsxwriter>=3.0
Requires-Dist: requests
Provides-Extra: dev
Requires-Dist: pytest>=6.0; extra == "dev"
Requires-Dist: pytest-cov; extra == "dev"
Requires-Dist: black; extra == "dev"
Requires-Dist: flake8; extra == "dev"
Requires-Dist: mypy; extra == "dev"
Requires-Dist: sphinx; extra == "dev"
Requires-Dist: sphinx-rtd-theme; extra == "dev"
Provides-Extra: docs
Requires-Dist: sphinx; extra == "docs"
Requires-Dist: sphinx-rtd-theme; extra == "docs"
Requires-Dist: myst-parser; extra == "docs"
Dynamic: license-file
